README
setup.py
bin/vtwt
vtwt/__init__.py
vtwt/_oauth.py
vtwt/_version.py
vtwt/block.py
vtwt/cli.py
vtwt/follow.py
vtwt/followers.py
vtwt/following.py
vtwt/grep.py
vtwt/retweet.py
vtwt/svc.py
vtwt/tweet.py
vtwt/unblock.py
vtwt/unfollow.py
vtwt/util.py
vtwt/watch.py
vtwt.egg-info/PKG-INFO
vtwt.egg-info/SOURCES.txt
vtwt.egg-info/dependency_links.txt
vtwt.egg-info/top_level.txt