Metadata-Version: 1.1
Name: vtwt
Version: 0.1.2
Summary: Ver's Twitter CLI
Home-page: http://github.com/olix0r/vtwt
Author: Oliver Gould
Author-email: ver@olix0r.net
License: MIT
Download-URL: http://pypi.python.org/pypi/vtwt
Platform: UNKNOWN
Classifier: Framework :: Twisted
Classifier: License :: OSI Approved :: MIT License
Requires: twittytwister
Requires: twisted
Requires: oauth
Requires: pendrell(>=0.2.2)
Requires: jersey(>=0.1.2)
Provides: vtwt
